{"strong":"H04725","word":"_*Mwqm*_ maqowm or _*Mqm*_ maqom also (fem.) _*hmwqm*_ m@qowmah _*hmqm*_ m@qomah","pronunciation":"maw-kome' maw-kome' mek-o-mah'mek-o-mah'","etymology":"from 06965","strong_reference":"H06965","source":"TWOT - 1999h","partOfSpeech":"n m","avSummary":"place 391, home 3, room 3, whithersoever 2, open 1, space 1, country 1","occurrence":402,"definition":"1) standing place, place\n    1a) standing place, station, post, office\n    1b) place, place of human abode\n    1c) city, land, region\n    1d) place, locality, spot\n    1e) space, room, distance\n    1f) region, quarter, direction\n    1g) give place to, instead of","timestamp":"2026-01-03T16:38:09.147Z"}